django_manticoresearch/__init__.py
django_manticoresearch/apps.py
django_manticoresearch/connection.py
django_manticoresearch/fields.py
django_manticoresearch/indexes.py
django_manticoresearch/registry.py
django_manticoresearch/signals.py
django_manticoresearch/management/__init__.py
django_manticoresearch/management/commands/__init__.py
django_manticoresearch/management/commands/indexing.py
django_manticoresearch-0.3.2.dist-info/licenses/LICENSE
django_manticoresearch-0.3.2.dist-info/METADATA
django_manticoresearch-0.3.2.dist-info/WHEEL
django_manticoresearch-0.3.2.dist-info/top_level.txt
django_manticoresearch-0.3.2.dist-info/RECORD
