Metadata-Version: 2.4
Name: django-manticoresearch
Version: 0.3.2
Summary: Django integration for Manticore Search
Home-page: https://github.com/michael7nightingale/django-manticoresearch
Author: michael7nightingale
Author-email: suslanchikmopl@gmail.com
Classifier: Development Status :: 3 - Alpha
Classifier: Framework :: Django
Classifier: Intended Audience :: Developers
Classifier: License :: OSI Approved :: MIT License
Classifier: Programming Language :: Python :: 3
Requires-Python: >=3.6
License-File: LICENSE
Requires-Dist: django>=3.2
Requires-Dist: manticoresearch>=3.0.0
Requires-Dist: ndjson>=0.3.1
Dynamic: author
Dynamic: author-email
Dynamic: classifier
Dynamic: description
Dynamic: description-content-type
Dynamic: home-page
Dynamic: license-file
Dynamic: requires-dist
Dynamic: requires-python
Dynamic: summary
